{
    "name": "vs-wal",
    "type": "dark",
    "colors": {
        "titleBar.activeBackground": "#384a26",
        "titleBar.activeForeground": "#d4d3d6",
        "titleBar.inactiveBackground": "#6B8636",
        "menu.background": "#949395",
        "menu.foreground": "#d4d3d6",
        "foreground": "#d4d3d6",
        "focusBorder": "#00000000",
        "editor.background": "#0F201D",
        "editor.foreground": "#d4d3d6",
        "editor.lineHighlightBorder": "#00000000",
        "editor.lineHighlightBackground": "#526c3730",
        "activityBarBadge.background": "#59675A",
        "sideBarTitle.foreground": "#d4d3d6",
        "sideBarTitle.background": "#384a26",
        "activityBar.background": "#384a26",
        "activityBar.dropBackground": "#6B8636",
        "activityBar.foreground": "#d4d3d6",
        "activityBarBadge.foreground": "#0F201D",
        "activityBarBadge.background": "#d4d3d6",
        "badge.foreground": "#d4d3d6",
        "badge.background": "#0F201D",
        "panel.border": "#526c37",
        "panel.background": "#0F201D",
        "panelTitle.activeForeground": "#d4d3d6",
        "panelTitle.inactiveForeground": "#d4d3d6",
        "terminal.background": "#0F201D",
        "terminal.foreground": "#d4d3d6",
        "terminal.ansiBlack": "#0F201D",
        "terminal.ansiRed": "#59675A",
        "terminal.ansiGreen": "#7D7B7F",
        "terminal.ansiYellow": "#6B8636",
        "terminal.ansiBlue": "#678845",
        "terminal.ansiMagenta": "#949845",
        "terminal.ansiCyan": "#99A0A8",
        "terminal.ansiWhite": "#d4d3d6",
        "terminal.ansiBrightBlack": "#949395",
        "terminal.ansiBrightRed": "#59675A",
        "terminal.ansiBrightGreen": "#7D7B7F",
        "terminal.ansiBrightYellow": "#6B8636",
        "terminal.ansiBrightBlue": "#678845",
        "terminal.ansiBrightMagenta": "#949845",
        "terminal.ansiBrightCyan": "#99A0A8",
        "terminal.ansiBrightWhite": "#d4d3d6",
        "sideBar.background": "#949395",
        "sideBar.foreground": "#d4d3d6",
        "statusBar.background": "#384a26",
        "statusBar.debuggingBackground": "#d4d3d6",
        "statusBar.debuggingForeground": "#0F201D",
        "statusBar.noFolderForeground": "#d4d3d6",
        "statusBar.noFolderBackground": "#0F201D",
        "statusBar.foreground": "#d4d3d6",
        "editorGroupHeader.tabsBackground": "#384a2660",
        "editorGroup.dropBackground": "#526c3760",
        "editorGroup.border": "#526c37",
        "tab.border": "#00000000",
        "tab.unfocusedActiveBorder": "#384a26",
        "tab.activeBackground": "#526c37",
        "tab.activeForeground": "#d4d3d6",
        "tab.inactiveBackground": "#384a26",
        "tab.inactiveForeground": "#d4d3d6",
        "tab.unfocusedActiveForeground": "#d4d3d680",
        "tab.unfocusedInactiveForeground": "#d4d3d680",
        "input.background": "#0F201D",
        "input.foreground": "#d4d3d6",
        "input.placeholderForeground": "#d4d3d6AA",
        "input.border": "#526c37",
        "dropdown.background": "#0F201D",
        "dropdown.foreground": "#d4d3d6",
        "dropdown.border": "#526c37",
        "progressBar.background": "#526c37",
        "button.background": "#526c37",
        "button.foreground": "#d4d3d6",
        "editorLink.activeForeground": "#6B8636",
        "editorLink.foreground": "#7D7B7F",
        "list.activeSelectionBackground": "#7D7B7FAA",
        "list.inactiveSelectionBackground": "#7D7B7F60",
        "list.focusBackground": "#7D7B7FAA",
        "list.hoverForeground": "#d4d3d6",
        "list.hoverBackground": "#7D7B7F30",
        "list.dropBackground": "#7D7B7F30",
        "notification.background": "#526c37",
        "notification.foreground": "#d4d3d6",
        "notification.buttonBackground": "#526c37",
        "notification.buttonForeground": "#d4d3d6",
        "editorWidget.background": "#949395",
        "editorWidget.border": "#00000000",
        "editorMarkerNavigation.background": "#384a26",
        "widget.shadow": "#00000000",
        "peekView.border": "#00000000",
        "peekViewEditor.background": "#949395",
        "peekViewEditor.matchHighlightBackground": "#526c37",
        "peekViewResult.background": "#384a26",
        "peekViewResult.matchHighlightBackground": "#526c37",
        "peekViewResult.selectionBackground": "#526c37",
        "peekViewTitle.background": "#526c37",
        "peekViewEditorGutter.background": "#949395"
    },
	"tokenColors": [
		{
			"settings": {
				"foreground": "#59675A",
				"background": "#0F201D"
			}
		},
		{
			"name": "Comment",
			"scope": [
				"comment",
				"punctuation.definition.comment"
			],
			"settings": {
				"fontStyle": "italic",
				"foreground": "#949395"
			}
		},
		{
			"name": "Variables",
			"scope": [
				"variable",
				"string constant.other.placeholder"
			],
			"settings": {
				"foreground": "#99A0A8"
			}
		},
		{
			"name": "Colors",
			"scope": [
				"constant.other.color"
			],
			"settings": {
				"foreground": "#d4d3d6"
			}
		},
		{
			"name": "Invalid",
			"scope": [
				"invalid",
				"invalid.illegal"
			],
			"settings": {
				"foreground": "#59675A"
			}
		},
		{
			"name": "Keyword, Storage",
			"scope": [
				"keyword",
				"storage.type",
				"storage.modifier"
			],
			"settings": {
				"foreground": "#7D7B7F"
			}
		},
		{
			"name": "Operator, Misc",
			"scope": [
				"keyword.control",
				"constant.other.color",
				"punctuation",
				"meta.tag",
				"punctuation.definition.tag",
				"punctuation.separator.inheritance.php",
				"punctuation.definition.tag.html",
				"punctuation.definition.tag.begin.html",
				"punctuation.definition.tag.end.html",
				"punctuation.section.embedded",
				"keyword.other.template",
				"keyword.other.substitution"
			],
			"settings": {
				"foreground": "#99A0A8"
			}
		},
		{
			"name": "Tag",
			"scope": [
				"entity.name.tag",
				"meta.tag.sgml",
				"markup.deleted.git_gutter"
			],
			"settings": {
				"foreground": "#59675A"
			}
		},
		{
			"name": "Function, Special Method",
			"scope": [
				"entity.name.function",
				"meta.function-call",
				"variable.function",
				"support.function",
				"keyword.other.special-method"
			],
			"settings": {
				"foreground": "#59675A"
			}
		},
		{
			"name": "Block Level Variables",
			"scope": [
				"meta.block variable.other"
			],
			"settings": {
				"foreground": "#59675A"
			}
		},
		{
			"name": "Other Variable, String Link",
			"scope": [
				"support.other.variable",
				"string.other.link"
			],
			"settings": {
				"foreground": "#59675A"
			}
		},
		{
			"name": "Number, Constant, Function Argument, Tag Attribute, Embedded",
			"scope": [
				"constant.numeric",
				"constant.language",
				"support.constant",
				"constant.character",
				"constant.escape",
				"variable.parameter",
				"keyword.other.unit",
				"keyword.other"
			],
			"settings": {
				"foreground": "#6B8636"
			}
		},
		{
			"name": "String, Symbols, Inherited Class, Markup Heading",
			"scope": [
				"string",
				"constant.other.symbol",
				"constant.other.key",
				"entity.other.inherited-class",
				"markup.heading",
				"markup.inserted.git_gutter",
				"meta.group.braces.curly constant.other.object.key.js string.unquoted.label.js"
			],
			"settings": {
				"fontStyle": "normal",
				"foreground": "#678845"
			}
		},
		{
			"name": "Class, Support",
			"scope": [
				"entity.name",
				"support.type",
				"support.class",
				"support.orther.namespace.use.php",
				"meta.use.php",
				"support.other.namespace.php",
				"markup.changed.git_gutter",
				"support.type.sys-types"
			],
			"settings": {
				"foreground": "#949845"
			}
		},
		{
			"name": "Entity Types",
			"scope": [
				"support.type"
			],
			"settings": {
				"foreground": "#99A0A8"
			}
		},
		{
			"name": "CSS Class and Support",
			"scope": [
				"source.css support.type.property-name",
				"source.sass support.type.property-name",
				"source.scss support.type.property-name",
				"source.less support.type.property-name",
				"source.stylus support.type.property-name",
				"source.postcss support.type.property-name"
			],
			"settings": {
				"foreground": "#99A0A8"
			}
		},
		{
			"name": "Sub-methods",
			"scope": [
				"entity.name.module.js",
				"variable.import.parameter.js",
				"variable.other.class.js"
			],
			"settings": {
				"foreground": "#59675A"
			}
		},
		{
			"name": "Language methods",
			"scope": [
				"variable.language"
			],
			"settings": {
				"fontStyle": "italic",
				"foreground": "#59675A"
			}
		},
		{
			"name": "entity.name.method.js",
			"scope": [
				"entity.name.method.js"
			],
			"settings": {
				"fontStyle": "italic",
				"foreground": "#678845"
			}
		},
		{
			"name": "meta.method.js",
			"scope": [
				"meta.class-method.js entity.name.function.js",
				"variable.function.constructor"
			],
			"settings": {
				"foreground": "#678845"
			}
		},
		{
			"name": "Attributes",
			"scope": [
				"entity.other.attribute-name"
			],
			"settings": {
				"foreground": "#949845"
			}
		},
		{
			"name": "HTML Attributes",
			"scope": [
				"text.html.basic entity.other.attribute-name.html",
				"text.html.basic entity.other.attribute-name"
			],
			"settings": {
				"fontStyle": "italic",
				"foreground": "#6B8636"
			}
		},
		{
			"name": "CSS Classes",
			"scope": [
				"entity.other.attribute-name.class"
			],
			"settings": {
				"foreground": "#6B8636"
			}
		},
		{
			"name": "CSS ID's",
			"scope": [
				"source.sass keyword.control"
			],
			"settings": {
				"foreground": "#678845"
			}
		},
		{
			"name": "Inserted",
			"scope": [
				"markup.inserted"
			],
			"settings": {
				"foreground": "#7D7B7F"
			}
		},
		{
			"name": "Deleted",
			"scope": [
				"markup.deleted"
			],
			"settings": {
				"foreground": "#59675A"
			}
		},
		{
			"name": "Changed",
			"scope": [
				"markup.changed"
			],
			"settings": {
				"foreground": "#949845"
			}
		},
		{
			"name": "Regular Expressions",
			"scope": [
				"string.regexp"
			],
			"settings": {
				"foreground": "#99A0A8"
			}
		},
		{
			"name": "Escape Characters",
			"scope": [
				"constant.character.escape"
			],
			"settings": {
				"foreground": "#99A0A8"
			}
		},
		{
			"name": "URL",
			"scope": [
				"*url*",
				"*link*",
				"*uri*"
			],
			"settings": {
				"fontStyle": "underline"
			}
		},
		{
			"name": "Decorators",
			"scope": [
				"tag.decorator.js entity.name.tag.js",
				"tag.decorator.js punctuation.definition.tag.js"
			],
			"settings": {
				"fontStyle": "italic",
				"foreground": "#678845"
			}
		},
		{
			"name": "ES7 Bind Operator",
			"scope": [
				"source.js constant.other.object.key.js string.unquoted.label.js"
			],
			"settings": {
				"fontStyle": "italic",
				"foreground": "#59675A"
			}
		},
		{
			"name": "JSON Key - Level 0",
			"scope": [
				"source.json meta.structure.dictionary.json support.type.property-name.json"
			],
			"settings": {
				"foreground": "#99A0A8"
			}
		},
		{
			"name": "JSON Key - Level 1",
			"scope": [
				"source.json meta.structure.dictionary.json meta.structure.dictionary.value.json meta.structure.dictionary.json support.type.property-name.json"
			],
			"settings": {
				"foreground": "#d4d3d6"
			}
		},
		{
			"name": "JSON Key - Level 2",
			"scope": [
				"source.json meta.structure.dictionary.json meta.structure.dictionary.value.json meta.structure.dictionary.json meta.structure.dictionary.value.json meta.structure.dictionary.json support.type.property-name.json"
			],
			"settings": {
				"foreground": "#949395"
			}
		},
		{
			"name": "JSON Key - Level 3",
			"scope": [
				"source.json meta.structure.dictionary.json meta.structure.dictionary.value.json meta.structure.dictionary.json meta.structure.dictionary.value.json meta.structure.dictionary.json meta.structure.dictionary.value.json meta.structure.dictionary.json support.type.property-name.json"
			],
			"settings": {
				"foreground": "#59675A"
			}
		},
		{
			"name": "JSON Key - Level 4",
			"scope": [
				"source.json meta.structure.dictionary.json meta.structure.dictionary.value.json meta.structure.dictionary.json meta.structure.dictionary.value.json meta.structure.dictionary.json meta.structure.dictionary.value.json meta.structure.dictionary.json meta.structure.dictionary.value.json meta.structure.dictionary.json support.type.property-name.json"
			],
			"settings": {
				"foreground": "#7D7B7F"
			}
		},
		{
			"name": "JSON Key - Level 5",
			"scope": [
				"source.json meta.structure.dictionary.json meta.structure.dictionary.value.json meta.structure.dictionary.json meta.structure.dictionary.value.json meta.structure.dictionary.json meta.structure.dictionary.value.json meta.structure.dictionary.json meta.structure.dictionary.value.json meta.structure.dictionary.json meta.structure.dictionary.value.json meta.structure.dictionary.json support.type.property-name.json"
			],
			"settings": {
				"foreground": "#678845"
			}
		},
		{
			"name": "JSON Key - Level 6",
			"scope": [
				"source.json meta.structure.dictionary.json meta.structure.dictionary.value.json meta.structure.dictionary.json meta.structure.dictionary.value.json meta.structure.dictionary.json meta.structure.dictionary.value.json meta.structure.dictionary.json meta.structure.dictionary.value.json meta.structure.dictionary.json meta.structure.dictionary.value.json meta.structure.dictionary.json meta.structure.dictionary.value.json meta.structure.dictionary.json support.type.property-name.json"
			],
			"settings": {
				"foreground": "#59675A"
			}
		},
		{
			"name": "JSON Key - Level 7",
			"scope": [
				"source.json meta.structure.dictionary.json meta.structure.dictionary.value.json meta.structure.dictionary.json meta.structure.dictionary.value.json meta.structure.dictionary.json meta.structure.dictionary.value.json meta.structure.dictionary.json meta.structure.dictionary.value.json meta.structure.dictionary.json meta.structure.dictionary.value.json meta.structure.dictionary.json meta.structure.dictionary.value.json meta.structure.dictionary.json meta.structure.dictionary.value.json meta.structure.dictionary.json support.type.property-name.json"
			],
			"settings": {
				"foreground": "#949845"
			}
		},
		{
			"name": "JSON Key - Level 8",
			"scope": [
				"source.json meta.structure.dictionary.json meta.structure.dictionary.value.json meta.structure.dictionary.json meta.structure.dictionary.value.json meta.structure.dictionary.json meta.structure.dictionary.value.json meta.structure.dictionary.json meta.structure.dictionary.value.json meta.structure.dictionary.json meta.structure.dictionary.value.json meta.structure.dictionary.json meta.structure.dictionary.value.json meta.structure.dictionary.json meta.structure.dictionary.value.json meta.structure.dictionary.json meta.structure.dictionary.value.json meta.structure.dictionary.json support.type.property-name.json"
			],
			"settings": {
				"foreground": "#7D7B7F"
			}
		},
		{
			"name": "Markdown - Plain",
			"scope": [
				"text.html.markdown",
				"punctuation.definition.list_item.markdown"
			],
			"settings": {
				"foreground": "#d4d3d6"
			}
		},
		{
			"name": "Markdown - Markup Raw Inline",
			"scope": [
				"text.html.markdown markup.inline.raw.markdown"
			],
			"settings": {
				"foreground": "#949845"
			}
		},
		{
			"name": "Markdown - Markup Raw Inline Punctuation",
			"scope": [
				"text.html.markdown markup.inline.raw.markdown punctuation.definition.raw.markdown"
			],
			"settings": {
				"foreground": "#949395"
			}
		},
		{
			"name": "Markdown - Line Break",
			"scope": [
				"text.html.markdown meta.dummy.line-break"
			],
			"settings": {
				"foreground": ""
			}
		},
		{
			"name": "Markdown - Heading",
			"scope": [
				"markdown.heading",
				"markup.heading | markup.heading entity.name",
				"markup.heading.markdown punctuation.definition.heading.markdown"
			],
			"settings": {
				"foreground": "#7D7B7F"
			}
		},
		{
			"name": "Markup - Italic",
			"scope": [
				"markup.italic"
			],
			"settings": {
				"fontStyle": "italic",
				"foreground": "#59675A"
			}
		},
		{
			"name": "Markup - Bold",
			"scope": [
				"markup.bold",
				"markup.bold string"
			],
			"settings": {
				"fontStyle": "bold",
				"foreground": "#59675A"
			}
		},
		{
			"name": "Markup - Bold-Italic",
			"scope": [
				"markup.bold markup.italic",
				"markup.italic markup.bold",
				"markup.quote markup.bold",
				"markup.bold markup.italic string",
				"markup.italic markup.bold string",
				"markup.quote markup.bold string"
			],
			"settings": {
				"fontStyle": "bold",
				"foreground": "#59675A"
			}
		},
		{
			"name": "Markup - Underline",
			"scope": [
				"markup.underline"
			],
			"settings": {
				"fontStyle": "underline",
				"foreground": "#7D7B7F"
			}
		},
		{
			"name": "Markup - Strike",
			"scope": [
				"markup.strike"
			],
			"settings": {
				"fontStyle": "strike",
				"foreground": ""
			}
		},
		{
			"name": "Markdown - Blockquote",
			"scope": [
				"markup.quote punctuation.definition.blockquote.markdown"
			],
			"settings": {
				"background": "#949395",
				"foreground": "#949395"
			}
		},
		{
			"name": "Markup - Quote",
			"scope": [
				"markup.quote"
			],
			"settings": {
				"fontStyle": "italic",
				"foreground": ""
			}
		},
		{
			"name": "Markdown - Link",
			"scope": [
				"string.other.link.title.markdown"
			],
			"settings": {
				"foreground": "#678845"
			}
		},
		{
			"name": "Markdown - Link Description",
			"scope": [
				"string.other.link.description.title.markdown"
			],
			"settings": {
				"foreground": "#949845"
			}
		},
		{
			"name": "Markdown - Link Anchor",
			"scope": [
				"constant.other.reference.link.markdown"
			],
			"settings": {
				"foreground": "#6B8636"
			}
		},
		{
			"name": "Markup - Raw Block",
			"scope": [
				"markup.raw.block"
			],
			"settings": {
				"foreground": "#949845"
			}
		},
		{
			"name": "Markdown - Raw Block Fenced",
			"scope": [
				"markup.raw.block.fenced.markdown"
			],
			"settings": {
				"foreground": "#d4d3d650"
			}
		},
		{
			"name": "Markdown - Fenced Bode Block",
			"scope": [
				"punctuation.definition.fenced.markdown"
			],
			"settings": {
				"foreground": "#d4d3d650"
			}
		},
		{
			"name": "Markdown - Fenced Bode Block Variable",
			"scope": [
				"markup.raw.block.fenced.markdown",
				"variable.language.fenced.markdown",
				"punctuation.section.class.end"
			],
			"settings": {
				"foreground": "#d4d3d6"
			}
		},
		{
			"name": "Markdown - Fenced Language",
			"scope": [
				"variable.language.fenced.markdown"
			],
			"settings": {
				"foreground": "#949395"
			}
		},
		{
			"name": "Markdown - Separator",
			"scope": [
				"meta.separator"
			],
			"settings": {
				"fontStyle": "bold",
				"background": "#d4d3d650",
				"foreground": "#949395"
			}
		},
		{
			"name": "Markup - Table",
			"scope": [
				"markup.table"
			],
			"settings": {
				"foreground": "#d4d3d6"
			}
		},
		{
			"scope": "token.info-token",
			"settings": {
				"foreground": "#99A0A8"
			}
		},
		{
			"scope": "token.warn-token",
			"settings": {
				"foreground": "#6B8636"
			}
		},
		{
			"scope": "token.error-token",
			"settings": {
				"foreground": "#59675A"
			}
		},
		{
			"scope": "token.debug-token",
			"settings": {
				"foreground": "#949845"
			}
		}
	]
}
